ansi_esc/__init__.py
ansi_esc/escape_char.py
ansi_esc/font/__init__.py
ansi_esc/font/esc.py
ansi_esc/font/colors/__init__.py
ansi_esc/font/colors/_color_id.py
ansi_esc/font/colors/background/__init__.py
ansi_esc/font/colors/background/_background.py
ansi_esc/font/colors/foreground/__init__.py
ansi_esc/font/colors/foreground/_foreground.py
ansi_esc/font/effects/__init__.py
ansi_esc/font/effects/_effects.py
ansi_esc/font/ideograms/__init__.py
ansi_esc/font/ideograms/_ideograms.py
ansi_esc-0.0.0.0.dist-info/METADATA
ansi_esc-0.0.0.0.dist-info/WHEEL
ansi_esc-0.0.0.0.dist-info/RECORD
